sql_batcher/__init__.py
sql_batcher/async_batcher.py
sql_batcher/async_query_collector.py
sql_batcher/batcher.py
sql_batcher/insert_merger.py
sql_batcher/query_collector.py
sql_batcher/retry.py
sql_batcher/adapters/__init__.py
sql_batcher/adapters/async_base.py
sql_batcher/adapters/async_bigquery.py
sql_batcher/adapters/async_postgresql.py
sql_batcher/adapters/async_snowflake.py
sql_batcher/adapters/async_trino.py
sql_batcher/adapters/base.py
sql_batcher/adapters/bigquery.py
sql_batcher/adapters/generic.py
sql_batcher/adapters/postgresql.py
sql_batcher/adapters/snowflake.py
sql_batcher/adapters/trino.py
sql_batcher-0.1.4.dist-info/licenses/LICENSE
sql_batcher-0.1.4.dist-info/METADATA
sql_batcher-0.1.4.dist-info/WHEEL
sql_batcher-0.1.4.dist-info/top_level.txt
sql_batcher-0.1.4.dist-info/RECORD
