Metadata-Version: 2.4
Name: sql-batcher
Version: 0.1.4
Summary: A Python library for batching SQL statements to optimize database operations
Author-email: SQL Batcher Team <info@sqlbatcher.com>
License: MIT
Project-URL: Homepage, https://github.com/brannn/sql-batcher
Project-URL: Documentation, https://github.com/brannn/sql-batcher
Project-URL: Bug Tracker, https://github.com/brannn/sql-batcher/issues
Project-URL: Source Code, https://github.com/brannn/sql-batcher
Classifier: Development Status :: 4 - Beta
Classifier: Intended Audience :: Developers
Classifier: Programming Language :: Python :: 3
Classifier: Programming Language :: Python :: 3.8
Classifier: Programming Language :: Python :: 3.9
Classifier: Programming Language :: Python :: 3.10
Classifier: Programming Language :: Python :: 3.11
Classifier: Topic :: Database
Classifier: Topic :: Software Development :: Libraries
Requires-Python: >=3.8
License-File: LICENSE
Requires-Dist: typing-extensions>=4.0.0; python_version < "3.9"
Provides-Extra: trino
Requires-Dist: trino>=0.310.0; extra == "trino"
Provides-Extra: snowflake
Requires-Dist: snowflake-connector-python>=2.7.0; extra == "snowflake"
Provides-Extra: spark
Requires-Dist: pyspark>=3.2.0; extra == "spark"
Provides-Extra: bigquery
Requires-Dist: google-cloud-bigquery>=3.0.0; extra == "bigquery"
Provides-Extra: postgresql
Requires-Dist: psycopg2-binary>=2.9.0; extra == "postgresql"
Provides-Extra: all
Requires-Dist: trino>=0.310.0; extra == "all"
Requires-Dist: snowflake-connector-python>=2.7.0; extra == "all"
Requires-Dist: pyspark>=3.2.0; extra == "all"
Requires-Dist: google-cloud-bigquery>=3.0.0; extra == "all"
Requires-Dist: psycopg2-binary>=2.9.0; extra == "all"
Provides-Extra: dev
Requires-Dist: pytest>=7.0.0; extra == "dev"
Requires-Dist: pytest-cov>=3.0.0; extra == "dev"
Requires-Dist: black>=22.3.0; extra == "dev"
Requires-Dist: isort>=5.10.0; extra == "dev"
Requires-Dist: mypy>=0.961; extra == "dev"
Requires-Dist: flake8>=4.0.0; extra == "dev"
Provides-Extra: docs
Requires-Dist: sphinx>=5.0.0; extra == "docs"
Requires-Dist: sphinx-rtd-theme>=1.0.0; extra == "docs"
Requires-Dist: sphinx-autodoc-typehints>=1.18.0; extra == "docs"
Dynamic: license-file
